coininfo/__init__.py
coininfo/info.py
coininfo-0.3.dist-info/METADATA
coininfo-0.3.dist-info/WHEEL
coininfo-0.3.dist-info/top_level.txt
coininfo-0.3.dist-info/RECORD
