Metadata-Version: 2.1
Name: coininfo
Version: 0.3
Requires-Dist: requests ==2.31.0
